{
  "ARCHITECT.moves.NOTHING.title": "Nulla",
  "ARCHITECT.name": "L'Architetto",
  "ASSASSIN_RUBY_RAIDER.moves.KILLSHOT.title": "Colpo mortale",
  "ASSASSIN_RUBY_RAIDER.name": "Assassino razziatore",
  "ATTACK_MOVE_MONSTER.moves.POKE.title": "Stoccata",
  "ATTACK_MOVE_MONSTER.name": "Mostro d'attacco",
  "AXEBOT.moves.BOOT_UP.title": "Accensione",
  "AXEBOT.moves.HAMMER_UPPERCUT.title": "Gancio martellante",
  "AXEBOT.moves.ONE_TWO.title": "Uno-due",
  "AXEBOT.moves.SHARPEN.title": "Affilatura",
  "AXEBOT.name": "Affettabot",
  "AXE_RUBY_RAIDER.moves.BIG_SWING.title": "Grande falciata",
  "AXE_RUBY_RAIDER.name": "Affettarazziatore",
  "BATTLE_FRIEND_V1.moves.NOTHING.title": "Nulla",
  "BATTLE_FRIEND_V1.name": "Partner da battaglia V1.0",
  "BATTLE_FRIEND_V2.moves.NOTHING.title": "Nulla",
  "BATTLE_FRIEND_V2.name": "Partner da battaglia V2.0",
  "BATTLE_FRIEND_V3.moves.NOTHING.title": "Nulla",
  "BATTLE_FRIEND_V3.name": "Partner da battaglia V3.0",
  "BIG_DUMMY.moves.NOTHING.title": "Nulla",
  "BIG_DUMMY.name": "Manichino grande",
  "BOWLBUG_EGG.moves.BITE.title": "Morso",
  "BOWLBUG_EGG.moves.PROTECT.title": "Protezione",
  "BOWLBUG_EGG.name": "Scaraciotola (Uovo)",
  "BOWLBUG_NECTAR.moves.BUFF.title": "Buff",
  "BOWLBUG_NECTAR.moves.THRASH.title": "Percossa",
  "BOWLBUG_NECTAR.moves.THRASH2.title": "Percossa",
  "BOWLBUG_NECTAR.name": "Scaraciotola (Nettare)",
  "BOWLBUG_ROCK.moves.HEADBUTT.title": "Testata",
  "BOWLBUG_ROCK.name": "Scaraciotola (Roccia)",
  "BOWLBUG_SILK.moves.SPIN_WEB.title": "Ragnatela rotante",
  "BOWLBUG_SILK.moves.THRASH.title": "Percossa",
  "BOWLBUG_SILK.name": "Scaraciotola (Seta)",
  "BRUTE_RUBY_RAIDER.moves.BEAT.title": "Colpo",
  "BRUTE_RUBY_RAIDER.moves.CLAP.title": "Colpetto",
  "BRUTE_RUBY_RAIDER.name": "Bruto razziatore",
  "BYGONE_EFFIGY.moves.SLASHES.title": "Squarcio",
  "BYGONE_EFFIGY.moves.SLEEP.speakLine1": "[red][sine]Il tuo viaggio termina qui..[/sine][/red]",
  "BYGONE_EFFIGY.moves.SLEEP.speakLine2": "Iniziamo?",
  "BYGONE_EFFIGY.moves.SLEEP.title": "Letargo",
  "BYGONE_EFFIGY.name": "Effige antica",
  "BYRDONIS.moves.BITE.title": "Morso",
  "BYRDONIS.moves.PECK.title": "Beccata",
  "BYRDONIS.moves.PROTECT.title": "Protezione",
  "BYRDONIS.name": "Gryfone",
  "BYRDONIS_NEST.moves.NOTHING.title": "Nulla",
  "BYRDONIS_NEST.name": "Nido",
  "BYRDPIP.moves.NOTHING.title": "Nulla",
  "BYRDPIP.name": "Gryfoncino",
  "CALCIFIED_CULTIST.moves.DARK_STRIKE.title": "Colpo oscuro",
  "CALCIFIED_CULTIST.moves.INCANTATION.banter": "[jitter]SEI TROPPO DEBOLE![/jitter]",
  "CALCIFIED_CULTIST.moves.INCANTATION.title": "Incantesimo",
  "CALCIFIED_CULTIST.name": "Accolito calcificato",
  "CEREMONIAL_BEAST.moves.BEAST_CRY.title": "Urlo bestiale",
  "CEREMONIAL_BEAST.moves.CRUSH.title": "Frantumazione",
  "CEREMONIAL_BEAST.moves.PLOW.title": "Aratura",
  "CEREMONIAL_BEAST.moves.STAMP.title": "Pedata",
  "CEREMONIAL_BEAST.moves.STOMP.title": "Pestone",
  "CEREMONIAL_BEAST.name": "Bestia solenne",
  "CHOMPER.moves.CLAMP.title": "Fissaggio",
  "CHOMPER.moves.SCREECH.title": "Stridio",
  "CHOMPER.moves.THRASH.title": "Percossa",
  "CHOMPER.name": "Mordicchio",
  "COCOON.moves.NOTHING.title": "Niente",
  "COCOON.name": "Bozzolo",
  "CORPSE_SLUG.moves.TACKLE.title": "Azione",
  "CORPSE_SLUG.moves.WHIP_SLAP.title": "Colpo di frusta",
  "CORPSE_SLUG.name": "Lumaca cadaverica",
  "CROSSBOW_RUBY_RAIDER.moves.FIRE.title": "Fuoco!",
  "CROSSBOW_RUBY_RAIDER.moves.RELOAD.title": "Ricarica",
  "CROSSBOW_RUBY_RAIDER.name": "Razziatore con balestra",
  "CRUSHER.moves.ADAPT.title": "Adattamento",
  "CRUSHER.moves.BUG_STING.title": "Puntura d'insetto",
  "CRUSHER.moves.ENLARGING_STRIKE.title": "Colpo ampliante",
  "CRUSHER.moves.GUARDED_STRIKE.title": "Colpo protettivo",
  "CRUSHER.moves.THRASH.title": "Percossa",
  "CRUSHER.name": "Spaccaossa",
  "CUBEX_CONSTRUCT.moves.CHARGE_UP.title": "Ricarica",
  "CUBEX_CONSTRUCT.moves.REPEATER_BLAST.title": "Raggio ripetitore",
  "CUBEX_CONSTRUCT.moves.SUBMERGE.title": "Immersione",
  "CUBEX_CONSTRUCT.name": "Assemblaggio cubico",
  "DAMP_CULTIST.moves.DARK_STRIKE.title": "Colpo oscuro",
  "DAMP_CULTIST.moves.INCANTATION.banter": "[jitter]AAH!\nAAAH[/jitter]",
  "DAMP_CULTIST.moves.INCANTATION.title": "Incantesimo",
  "DAMP_CULTIST.name": "Accolito zuppo",
  "DECIMILLIPEDE_SEGMENT.moves.BULK.title": "Crescita",
  "DECIMILLIPEDE_SEGMENT.moves.DEAD.title": "Morte",
  "DECIMILLIPEDE_SEGMENT.moves.OUTGAS.title": "Gas",
  "DECIMILLIPEDE_SEGMENT.moves.REATTACH.title": "Ricomposizione",
  "DECIMILLIPEDE_SEGMENT.moves.TACKLE.title": "Azione",
  "DECIMILLIPEDE_SEGMENT.moves.WRITHE.title": "Convulsioni",
  "DECIMILLIPEDE_SEGMENT.name": "Diecimilapiedi",
  "DEVOTED_SCULPTOR.moves.FORBIDDEN_INCANTATION": "Incantesimo proibito",
  "DEVOTED_SCULPTOR.moves.FORBIDDEN_INCANTATION.banter": "[jitter]AAAH![/jitter]",
  "DEVOTED_SCULPTOR.moves.SAVAGE": "Ferocia",
  "DEVOTED_SCULPTOR.name": "Scultore devoto",
  "DOOR.moves.DOOR_SLAM": "Sbatti-porta",
  "DOOR.moves.DRAMATIC_OPEN": "Apertura drammatica",
  "DOOR.moves.ENFORCE": "Costrizione",
  "DOOR.name": "Porta",
  "DOORMAKER.moves.GET_BACK_IN": "Torna dentro",
  "DOORMAKER.moves.GET_BACK_IN.deadDoorSpeakLine": "Un giorno ti prenderò...",
  "DOORMAKER.moves.WHAT_IS_IT": "Che succede",
  "DOORMAKER.moves.WHAT_IS_IT.deadDoorSpeakLine": "LA MIA PORTA!!!",
  "DOORMAKER.moves.WHAT_IS_IT.speakLine1": "Cosa! Di nuovo tu!?",
  "DOORMAKER.moves.WHAT_IS_IT.speakLine2": "Cosa ci fai ancora qui!",
  "DOORMAKER.moves.WHAT_IS_IT.speakLineInitial": "Chi va là!?",
  "DOORMAKER.name": "Fabbricaporte",
  "ENTOMANCER.moves.AGITATE_SWARM.title": "Sciame furioso",
  "ENTOMANCER.moves.BEES.title": "Apiii!",
  "ENTOMANCER.moves.PHEROMONE_SPIT.title": "Sputo di feromoni",
  "ENTOMANCER.moves.SPEAR.title": "Lancia!",
  "ENTOMANCER.name": "Coleomago",
  "EXOSKELETON.moves.ENRAGE.title": "Ira",
  "EXOSKELETON.moves.MANDIBLES.title": "Mandibole",
  "EXOSKELETON.moves.SKITTER.title": "Tagliare la corda",
  "EXOSKELETON.name": "Esoscheletro",
  "EYE_WITH_TEETH.moves.DISTRACT.title": "Distrazione",
  "EYE_WITH_TEETH.moves.STARTLE.title": "Sorpresa",
  "EYE_WITH_TEETH.name": "Occhio dentato",
  "FABRICATOR.moves.DISINTEGRATE.title": "Disintegrazione",
  "FABRICATOR.moves.FABRICATE.title": "Fabricazione",
  "FABRICATOR.name": "Mechacostruttore",
  "FAKE_MERCHANT_MONSTER.moves.ENRAGE.speakLine1": "Oh, la pagherai cara...",
  "FAKE_MERCHANT_MONSTER.moves.ENRAGE.speakLine2": "Ti seppellirò nei Moli Funesti!",
  "FAKE_MERCHANT_MONSTER.moves.ENRAGE.title": "Ira",
  "FAKE_MERCHANT_MONSTER.moves.SPEW_COINS.speakLine1": "JACKPOT!",
  "FAKE_MERCHANT_MONSTER.moves.SPEW_COINS.title": "Lanciamonete",
  "FAKE_MERCHANT_MONSTER.moves.SWIPE.speakLine1": "Sopra la testa!",
  "FAKE_MERCHANT_MONSTER.moves.SWIPE.title": "Scippo",
  "FAKE_MERCHANT_MONSTER.moves.THROW_RELIC.speakLine1": "Le vuoi? Prendile!",
  "FAKE_MERCHANT_MONSTER.moves.THROW_RELIC.title": "Lancio delle reliquie",
  "FAKE_MERCHANT_MONSTER.name": "Il mercante???",
  "FAT_GREMLIN.moves.FLEE.banter": "[jitter][orange]Taglio la corda![/orange][/jitter]",
  "FAT_GREMLIN.moves.FLEE.title": "Fuga",
  "FAT_GREMLIN.name": "Gremlin grasso",
  "FLAIL_KNIGHT.moves.BREAKER.title": "Distruzione",
  "FLAIL_KNIGHT.moves.FLAIL.title": "Flagello",
  "FLAIL_KNIGHT.moves.RAM.title": "Urto",
  "FLAIL_KNIGHT.name": "Cavaliere flagellatore",
  "FLYCONID.moves.FRAIL_SPORES.title": "Spore fragili",
  "FLYCONID.moves.SMASH.title": "Annientamento",
  "FLYCONID.moves.TACKLE.WEAKENING_SPORES.title": "Spore debilitanti",
  "FLYCONID.name": "Fungalato",
  "FOGMOG.moves.ILLUSORY_SPORES.title": "Spore illusorie",
  "FOGMOG.moves.THWACK.title": "Botta",
  "FOGMOG.name": "Fungonebbia",
  "FOSSIL_STALKER.moves.LASH.title": "Sferzata",
  "FOSSIL_STALKER.moves.LATCH.title": "Fissaggio",
  "FOSSIL_STALKER.moves.TACKLE.title": "Azione",
  "FOSSIL_STALKER.name": "Cacciatore di fossili",
  "FROG_KNIGHT.moves.BEETLE_CHARGE.title": "Carica scarabeo",
  "FROG_KNIGHT.moves.FOR_THE_QUEEN.title": "Per la regina",
  "FROG_KNIGHT.moves.STRIKE_DOWN_EVIL.title": "Espiare il male",
  "FROG_KNIGHT.moves.TONGUE_LASH.title": "Sferzata con lingua",
  "FROG_KNIGHT.name": "Rana cavaliere",
  "FUZZY_WURM_CRAWLER.moves.ACID_GOOP.title": "Acido appiccicoso",
  "FUZZY_WURM_CRAWLER.moves.TACKLE.INHALE_MOVE.title": "Inalazione",
  "FUZZY_WURM_CRAWLER.name": "Peloverme",
  "GAS_BOMB.moves.EXPLODE.title": "Esplosione",
  "GAS_BOMB.name": "Gasbomba",
  "GAZING_MOTH.moves.GLARE.title": "Sguardo",
  "GAZING_MOTH.moves.POWDER.title": "Polvere",
  "GAZING_MOTH.name": "Falena osservatrice",
  "GEM_EATER.moves.FOCUS_BEAM.title": "Raggio focalizzato",
  "GEM_EATER.moves.GEM_LASER.title": "Laser gemma",
  "GEM_EATER.name": "Divoragemme",
  "GLOBE_HEAD.moves.CHANNEL_LIGHTNING.title": "Luce canalizzata",
  "GLOBE_HEAD.moves.DUAL_CAST.title": "Evocazione doppia",
  "GLOBE_HEAD.moves.SHOCKING_SLAP.title": "Schiaffo scioccante",
  "GLOBE_HEAD.name": "Testaglobo",
  "GREMLIN_MERC.moves.DOUBLE_SMASH.title": "Doppio colpo",
  "GREMLIN_MERC.moves.GIMME.banter": "[jitter][gold]Soldi![/gold][/jitter]\n[sine][orange]Soldi![/orange][/sine]",
  "GREMLIN_MERC.moves.GIMME.title": "Dammi",
  "GREMLIN_MERC.moves.HEHE.title": "Eheh",
  "GREMLIN_MERC.name": "Gremlin mercenario",
  "GUARDBOT.moves.GUARD.title": "Guardia",
  "GUARDBOT.name": "Guardiabot",
  "HATCHLING.name": "Schiusa",
  "HAUNTED_SHIP.moves.HAUNT.title": "Infestazione",
  "HAUNTED_SHIP.moves.RAMMING_SPEED.title": "Velocità di speronamento",
  "HAUNTED_SHIP.moves.STOMP.title": "Pestone",
  "HAUNTED_SHIP.moves.SWIPE.title": "Scippo",
  "HAUNTED_SHIP.name": "Nave infestata",
  "HUNTER_KILLER.moves.BITE.title": "Morso",
  "HUNTER_KILLER.moves.PUNCTURE.title": "Puntura",
  "HUNTER_KILLER.moves.TENDERIZING_GOOP.title": "Succo di decomposizione",
  "HUNTER_KILLER.name": "Predatore di cacciatori",
  "INFESTED_PRISM.moves.JAB.title": "Colpo secco",
  "INFESTED_PRISM.moves.PULSATE.title": "Pulsazione",
  "INFESTED_PRISM.moves.RADIATE.title": "Radiazione",
  "INFESTED_PRISM.moves.WHIRLWIND.title": "Vortice",
  "INFESTED_PRISM.name": "Prisma infestato",
  "INKLET.moves.JAB.title": "Colpo secco",
  "INKLET.moves.PIERCING_GAZE.title": "Sguardo penetrante",
  "INKLET.moves.WINDUP_PUNCH.title": "Pugno a carica",
  "INKLET.name": "Inchiostrino",
  "KIN_FOLLOWER.moves.BOOMERANG_MOVE.title": "Boomerang",
  "KIN_FOLLOWER.moves.POWER_DANCE_MOVE.title": "Danza potente",
  "KIN_FOLLOWER.moves.QUICK_SLASH_MOVE.title": "Sferzata rapida",
  "KIN_FOLLOWER.name": "Discepolo della tribù",
  "KIN_PRIEST.followersDeathLine": "Impossibile!",
  "KIN_PRIEST.moves.BEAM_MOVE.title": "Raggio dell'anima",
  "KIN_PRIEST.moves.OR_OF_FRAILTY_MOVE.title": "Globo della fragilità",
  "KIN_PRIEST.moves.OR_OF_WEAKNESS_MOVE.title": "Globo della debolezza",
  "KIN_PRIEST.moves.RITUAL.speakLine1": "[jitter]Ka Quaww!!![/jitter]",
  "KIN_PRIEST.moves.RITUAL_MOVE.title": "Rituale oscuro",
  "KIN_PRIEST.name": "Sacerdote della tribù",
  "KNOWLEDGE_DEMON.moves.BLUE_FLAME.title": "Fiamma blu",
  "KNOWLEDGE_DEMON.moves.CURSE_OF_KNOWLEDGE.doneLine": "È fatta.",
  "KNOWLEDGE_DEMON.moves.CURSE_OF_KNOWLEDGE.startLine": "Fai la tua scelta.",
  "KNOWLEDGE_DEMON.moves.CURSE_OF_KNOWLEDGE.title": "Maledizione della conoscenza",
  "KNOWLEDGE_DEMON.moves.HAVE_A_TASTE.title": "Assaggio del dolore",
  "KNOWLEDGE_DEMON.moves.KNOWLEDGE_OVERWHELMING.title": "Conoscenza travolgente",
  "KNOWLEDGE_DEMON.moves.PONDER.title": "Riflessione",
  "KNOWLEDGE_DEMON.name": "Demone onnisciente",
  "LAGAVULIN_MATRIARCH.moves.DISEMBOWEL.title": "Sventramento",
  "LAGAVULIN_MATRIARCH.moves.SLASH.title": "Sferzata",
  "LAGAVULIN_MATRIARCH.moves.SLEEP.title": "Riposo",
  "LAGAVULIN_MATRIARCH.moves.SOUL_SIPHON.title": "Sottrazione dell'anima",
  "LAGAVULIN_MATRIARCH.name": "Matriarca Lagavulin",
  "LEAF_SLIME_M.moves.CLUMP_SHOT.title": "Colpo a gruppo",
  "LEAF_SLIME_M.moves.STICKY_SHOT.title": "Colpo appiccicoso",
  "LEAF_SLIME_M.name": "Melmerba (grande)",
  "LEAF_SLIME_S.moves.GOOP.title": "Gelatina",
  "LEAF_SLIME_S.moves.TACKLE.title": "Azione",
  "LEAF_SLIME_S.name": "Melmerba (piccola)",
  "LIVING_FOG.moves.BLOAT.title": "Rigonfiamento",
  "LIVING_FOG.name": "Nebbia vivente",
  "LIVING_SHIELD.moves.SHIELD_SLAM.title": "Colpo con scudo",
  "LIVING_SHIELD.name": "Scudo vivente",
  "LOUSE_PROGENITOR.moves.ACID_DUST.title": "Polvere acida",
  "LOUSE_PROGENITOR.moves.CURL_AND_GROW.title": "Arriccia e cresci",
  "LOUSE_PROGENITOR.moves.WEB_CANNON.title": "Cannone di ragnatele",
  "LOUSE_PROGENITOR.name": "Antenato delle pulci",
  "MAGI_KNIGHT.moves.MAGIC_BOMB.title": "Bomba magica",
  "MAGI_KNIGHT.moves.POWER_SHIELD.title": "Scudo del potere",
  "MAGI_KNIGHT.moves.RAM.title": "Incornata",
  "MAGI_KNIGHT.name": "Magicavaliere",
  "MAWLER.moves.CLAW.title": "Artiglio",
  "MAWLER.moves.RIP_AND_TEAR.title": "Strappo e lacerazione",
  "MAWLER.moves.ROAR.title": "Ruggito",
  "MAWLER.name": "Laceracarne",
  "MECHA_KNIGHT.SHIELDS_DOWN.dialogue": "Gli scudi sono abbassati!",
  "MECHA_KNIGHT.SHIELDS_UP.dialogue": "Gli scudi sono tornati!",
  "MECHA_KNIGHT.moves.CHARGE.title": "Carica",
  "MECHA_KNIGHT.moves.FLAMETHROWER.title": "Lanciafiamme",
  "MECHA_KNIGHT.moves.HEAVY_CLEAVE.title": "Mazzata pesante",
  "MECHA_KNIGHT.moves.WINDUP.title": "Carica",
  "MECHA_KNIGHT.name": "Cavaliere meccanico",
  "MOCK_ATTACK_AND_SUMMON_MINION_MONSTER.moves.ATTACK_AND_SUMMON_MINION.title": "Attacco ed Invocazione del seguace",
  "MOCK_ATTACK_AND_SUMMON_MINION_MONSTER.name": "Attacco ed Invocazione del Seguace Mostro",
  "MOCK_ATTACK_MONSTER.moves.ATTACK.title": "Attacco",
  "MOCK_ATTACK_MONSTER.name": "Attacco mostro",
  "MYSTERIOUS_KNIGHT.moves.BREAKER.title": "Distruttore",
  "MYSTERIOUS_KNIGHT.moves.FLAIL.title": "Flagello",
  "MYSTERIOUS_KNIGHT.moves.RAM.title": "Incornata",
  "MYSTERIOUS_KNIGHT.name": "Cavaliere misterioso",
  "MYTE.moves.BIG_SUCK.title": "Risucchio profondo",
  "MYTE.moves.BITE.title": "Morso",
  "MYTE.moves.SUCK.title": "Risucchio",
  "MYTE.moves.TOXIC.title": "Abbondanza tossica",
  "MYTE.name": "Acaro",
  "NIBBIT.moves.BUTT.title": "Didietro",
  "NIBBIT.moves.HESITANT_SLICE.title": "Colpo esitante",
  "NIBBIT.moves.HISS.title": "Sibillio",
  "NIBBIT.name": "Sgranocchiatore",
  "NOISEBOT.moves.NOISE.title": "Suono",
  "NOISEBOT.name": "Suonobot",
  "OSTY.name": "Osty",
  "OVICOPTER.moves.LAY_EGGS.title": "Deposizione delle uova",
  "OVICOPTER.moves.NUTRITIONAL_PASTE.title": "Pasto nutriente",
  "OVICOPTER.moves.SMASH.title": "Colpo",
  "OVICOPTER.moves.TENDERIZER.title": "Batticarne",
  "OVICOPTER.name": "Ovicoptero",
  "OWL_MAGISTRATE.moves.JUDICIAL_FLIGHT.title": "Volo del giudizio",
  "OWL_MAGISTRATE.moves.MAGISTRATE_SCRUTINY.title": "Sguardo magistrale",
  "OWL_MAGISTRATE.moves.PECK_ASSAULT.title": "Assalto a beccate",
  "OWL_MAGISTRATE.moves.VERDICT.title": "Verdetto",
  "OWL_MAGISTRATE.name": "Giudice gufo",
  "PAELS_LEGION.moves.NOTHING.title": "Nulla",
  "PAELS_LEGION.name": "Legione di Pael",
  "PARAFRIGHT.moves.SLAM.title": "Colpo",
  "PARAFRIGHT.name": "Seminaterrore",
  "PHANTASMAL_GARDENER.moves.BITE.title": "Morso",
  "PHANTASMAL_GARDENER.moves.ENLARGE.title": "Ingrandimento",
  "PHANTASMAL_GARDENER.moves.FLAIL.title": "Flagello",
  "PHANTASMAL_GARDENER.moves.LASH.title": "Sferzata",
  "PHANTASMAL_GARDENER.name": "Giardiniere spettrale",
  "PHROG_PARASITE.moves.INFECT.title": "Infezione",
  "PHROG_PARASITE.moves.LASH.title": "Sferzata",
  "PHROG_PARASITE.moves.LEAP_SLAM.title": "Saltoschianto",
  "PHROG_PARASITE.name": "Parassita fungineo",
  "PUNCH_CONSTRUCT.moves.FAST_PUNCH.title": "Pugno rapido",
  "PUNCH_CONSTRUCT.moves.READY.title": "IN POSIZIONE",
  "PUNCH_CONSTRUCT.moves.STRONG_PUNCH.title": "Pugno potente",
  "PUNCH_CONSTRUCT.name": "Assemblaggio pugile",
  "QUEEN.amalgamDeathSpeakLine": "...",
  "QUEEN.banter": "[jitter]Non mi sfuggirai![/jitter]",
  "QUEEN.moves.BARRIER.title": "Barriera",
  "QUEEN.moves.BURN_BRIGHT_FOR_ME.title": "Brucia luminoso per me",
  "QUEEN.moves.EXECUTION.title": "Esecuzione",
  "QUEEN.moves.IMPOSSIBLE.title": "Impossibile",
  "QUEEN.moves.OFF_WITH_YOUR_HEAD.title": "Gigliottina",
  "QUEEN.moves.SUMMON_1.title": "Invocazione",
  "QUEEN.moves.SUMMON_2.title": "Invocazione",
  "QUEEN.moves.YOURE_MINE.title": "Sei tra le mie grinfie",
  "QUEEN.name": "Regina funesta",
  "ROCKET.moves.CHARGE_UP.title": "Ricarica",
  "ROCKET.moves.LASER.title": "Laser",
  "ROCKET.moves.PRECISION_BEAM.title": "Raggio di precisione",
  "ROCKET.moves.RECHARGE.title": "Ricarica",
  "ROCKET.moves.TARGETING_RETICLE.title": "Mirino",
  "ROCKET.name": "Razzo",
  "SCROLL_OF_BITING.moves.CHEW.title": "Masticamento",
  "SCROLL_OF_BITING.moves.CHOMP.title": "Sgranocchio",
  "SCROLL_OF_BITING.moves.MORE_TEETH.title": "Denti a non finire",
  "SCROLL_OF_BITING.name": "Pergamena mordente",
  "SEAPUNK.moves.BUBBLE_BURP.title": "Sparabolle",
  "SEAPUNK.moves.SEA_KICK.title": "Calcio marino",
  "SEAPUNK.moves.SPINNING_KICK.title": "Calcio rotante",
  "SEAPUNK.name": "Teppista marino",
  "SEWER_CLAM.moves.JET.title": "Jet",
  "SEWER_CLAM.moves.PRESSURIZE.title": "Pressione",
  "SEWER_CLAM.name": "Vongola di fogna",
  "SHRINKER_BEETLE.moves.CHOMP.title": "Sgranocchio",
  "SHRINKER_BEETLE.moves.SHRINKER.title": "Riduttore",
  "SHRINKER_BEETLE.moves.STOMP.title": "Pestone",
  "SHRINKER_BEETLE.name": "Scarabeo restringente",
  "SKULKING_COLONY.moves.INERTIA.title": "Inerzia",
  "SKULKING_COLONY.moves.SUPER_CRAB.title": "Super granchio",
  "SKULKING_COLONY.moves.ZOOM.title": "Velocità",
  "SKULKING_COLONY.name": "Colonia furtiva",
  "SLIMED_BERSERKER.moves.FURIOUS_PUMMELING": "Pestaggio furioso",
  "SLIMED_BERSERKER.moves.SLIME_WHIRLWIND": "Vortice di melma",
  "SLIMED_BERSERKER.moves.VOMIT_ICHOR": "Vomito di icore",
  "SLIMED_BERSERKER.name": "Berserker viscido",
  "SLITHERING_STRANGLER.moves.CONSTRICT.title": "Costrizione",
  "SLITHERING_STRANGLER.moves.LASH.title": "Sferzata",
  "SLITHERING_STRANGLER.moves.THWACK.title": "Colpo secco",
  "SLITHERING_STRANGLER.name": "Strangolatore strisciante",
  "SLUDGE_SPINNER.moves.OIL_SPRAY.title": "Spray olioso",
  "SLUDGE_SPINNER.moves.RAGE.title": "Furia",
  "SLUDGE_SPINNER.moves.SLAM.title": "Botta",
  "SLUDGE_SPINNER.name": "Poltiglia rotante",
  "SLUMBERING_BEETLE.moves.CRASH.title": "Collisione",
  "SLUMBERING_BEETLE.moves.RESOLVE.title": "Determinazione",
  "SLUMBERING_BEETLE.moves.ROLL_OUT.title": "Rotolamento",
  "SLUMBERING_BEETLE.moves.SNORE.title": "Ronfo",
  "SLUMBERING_BEETLE.name": "Scarabeo dormiente",
  "SNAPPING_JAXFRUIT.moves.COLLECT_POWER.title": "Accumulo di potere",
  "SNAPPING_JAXFRUIT.moves.ENERGY_ORB.title": "Globo d'energia",
  "SNAPPING_JAXFRUIT.name": "Bulbo azzannatore",
  "SNEAKY_GREMLIN.moves.TACKLE.title": "Azione",
  "SNEAKY_GREMLIN.name": "Gremlin furtivo",
  "SOUL_FYSH.moves.BURP.title": "Eruttazione",
  "SOUL_FYSH.moves.DE_GAS.title": "Fuoriuscita di gas",
  "SOUL_FYSH.moves.SCREAM.title": "Urlo",
  "SOUL_FYSH.name": "Animapesce",
  "SOUL_NEXUS.moves.DRAIN_LIFE.title": "Prosciugamento vitale",
  "SOUL_NEXUS.moves.MAELSTROM.title": "Turbine",
  "SOUL_NEXUS.moves.SOUL_BURN.title": "Brucianima",
  "SOUL_NEXUS.name": "Nesso dell'anima",
  "SPECTRAL_KNIGHT.moves.HEX.title": "Sortilegio",
  "SPECTRAL_KNIGHT.moves.SOUL_FLAME.title": "Fiamma dell'anima",
  "SPECTRAL_KNIGHT.moves.SOUL_SLASH.title": "Sferzata dell'anima",
  "SPECTRAL_KNIGHT.name": "Cavaliere spettrale",
  "SPINY_TOAD.moves.PROTRUDING_SPIKES.title": "Punte sporgenti",
  "SPINY_TOAD.moves.SPIKE_EXPLOSION.title": "Esplosione di spine",
  "SPINY_TOAD.moves.TONGUE_LASH.title": "Sferzata con lingua",
  "SPINY_TOAD.name": "Rospo spinoso",
  "STABBOT.moves.STAB.title": "Pugnalata",
  "STABBOT.name": "Pugnalebot",
  "TERROR_EEL.moves.Crash.title": "Schianto",
  "TERROR_EEL.moves.Thrash.title": "Percossa",
  "TERROR_EEL.name": "Anguilla nefasta",
  "TEST_SUBJECT.moves.BIG_POUNCE_MOVE.title": "Salto feroce",
  "TEST_SUBJECT.moves.BITE_MOVE.title": "Morso",
  "TEST_SUBJECT.moves.BURNING_GROWL_MOVE.title": "Ruggito bruciante",
  "TEST_SUBJECT.moves.MULTI_CLAW_MOVE.title": "Multi-artiglio",
  "TEST_SUBJECT.moves.PHASE3_LACERATE_MOVE.title": "Lacerazione",
  "TEST_SUBJECT.moves.POUNCE_MOVE.title": "Salto",
  "TEST_SUBJECT.moves.RESPAWN_MOVE.title": "Riapparizione",
  "TEST_SUBJECT.moves.SKULL_BASH_MOVE.title": "Colpo di cranio",
  "TEST_SUBJECT.name": "Soggetto di prova #C{Count}",
  "THE_ADVERSARY_MK_ONE.moves.BARRAGE.title": "Sbarramento",
  "THE_ADVERSARY_MK_ONE.moves.BEAM.title": "Raggio",
  "THE_ADVERSARY_MK_ONE.moves.SMASH.title": "Colpo",
  "THE_ADVERSARY_MK_ONE.name": "L'Avversario Mk 1",
  "THE_ADVERSARY_MK_THREE.moves.BARRAGE.title": "Sbarramento",
  "THE_ADVERSARY_MK_THREE.moves.CRASH.title": "Colpo",
  "THE_ADVERSARY_MK_THREE.moves.FLAME_BEAM.title": "Raggio di fiamma",
  "THE_ADVERSARY_MK_THREE.name": "Avversario Mk 3",
  "THE_ADVERSARY_MK_TWO.moves.BARRAGE.title": "Sbarramento",
  "THE_ADVERSARY_MK_TWO.moves.BASH.title": "Botta",
  "THE_ADVERSARY_MK_TWO.moves.FLAME_BEAM.title": "Raggio di fiamme",
  "THE_ADVERSARY_MK_TWO.name": "Avversario Mk 2",
  "THE_ARM.moves.GRAB.title": "Presa",
  "THE_ARM.moves.PUNCH.title": "Pugno",
  "THE_ARM.moves.WRESTLE.title": "Lotta",
  "THE_ARM.name": "Il Braccio",
  "THE_BELL.moves.CACOPHONY.title": "Cacofonia",
  "THE_BELL.moves.CLANG.title": "Risonanza",
  "THE_BELL.moves.RING.title": "Suono",
  "THE_BELL.name": "La Campana",
  "THE_DREAMER.moves.DREAM.title": "Sogno",
  "THE_DREAMER.moves.FEND_OFF.title": "Respinta",
  "THE_DREAMER.moves.RUMINATE.title": "Meditazione",
  "THE_DREAMER.moves.SNORE.title": "Ronfo",
  "THE_DREAMER.name": "Il Sognatore",
  "THE_FORGOTTEN.moves.DREAD.title": "Angoscia",
  "THE_FORGOTTEN.moves.MIASMA.title": "Miasma",
  "THE_FORGOTTEN.name": "Il Dimenticato",
  "THE_INSATIABLE.moves.LIQUIFY_GROUND.title": "Liquifazione del suolo",
  "THE_INSATIABLE.moves.LUNGING_BITE.title": "Morso con affondo",
  "THE_INSATIABLE.moves.SALIVATE.title": "Salivazione",
  "THE_INSATIABLE.moves.THRASH.title": "Percossa",
  "THE_INSATIABLE.name": "L'Insaziabile",
  "THE_LOST.moves.DEBILITATING_SMOG.title": "Smog debilitante",
  "THE_LOST.moves.EYE_LASERS.title": "Laser oculari",
  "THE_LOST.name": "Il Perduto",
  "THE_OBSCURA.moves.HARDENING_STRIKE.title": "Colpo temprante",
  "THE_OBSCURA.moves.ILLUSION.title": "Illusione",
  "THE_OBSCURA.moves.PIERCING_GAZE.title": "Sguardo penetrante",
  "THE_OBSCURA.moves.WAIL.title": "Pianto",
  "THE_OBSCURA.name": "L'Obscura",
  "THIEVING_HOPPER.moves.ESCAPE.title": "Fuga",
  "THIEVING_HOPPER.moves.FLUTTER.title": "Palpitazione",
  "THIEVING_HOPPER.moves.HAT_TRICK.title": "Triplo colpo",
  "THIEVING_HOPPER.moves.NAB.title": "Agguantare",
  "THIEVING_HOPPER.moves.THIEVERY.title": "Furto",
  "THIEVING_HOPPER.name": "Mantide ladra",
  "TOADPOLE.moves.SPIKEN.title": "Spine",
  "TOADPOLE.moves.SPIKE_SPIT.title": "Raffica di spine",
  "TOADPOLE.moves.WHIRL.title": "Turbine",
  "TOADPOLE.name": "Girino",
  "TORCH_HEAD_AMALGAM.moves.TACKLE.title": "Azione",
  "TORCH_HEAD_AMALGAM.name": "Torciamostro",
  "TOUGH_EGG.moves.HATCH.title": "SCHIUSA",
  "TOUGH_EGG.name": "Uovo forte",
  "TRACKER_RUBY_RAIDER.moves.HOUNDS.title": "Scatena i segugi",
  "TRACKER_RUBY_RAIDER.moves.TRACK.title": "Inseguimento",
  "TRACKER_RUBY_RAIDER.name": "Razziatore inseguitore",
  "TUNNELER.moves.BELOW.title": "Attacco dal basso",
  "TUNNELER.moves.BITE.title": "Morso",
  "TUNNELER.moves.BURROW.title": "Nascondiglio",
  "TUNNELER.moves.STRIKE.title": "Colpo emergente",
  "TUNNELER.name": "Scavatore",
  "TURRET_OPERATOR.moves.LOADING.title": "Caricamento",
  "TURRET_OPERATOR.moves.UNLOAD.title": "Sfogo!",
  "TURRET_OPERATOR.name": "Operatorretta",
  "TWIG_SLIME_M.moves.CHOMP.title": "Sgranocchio",
  "TWIG_SLIME_M.moves.POKEY_POUNCE.title": "Piccolo salto",
  "TWIG_SLIME_M.moves.STICKY_SHOT.title": "Colpo appiccicoso",
  "TWIG_SLIME_M.name": "Ramomelma (grande)",
  "TWIG_SLIME_S.moves.GOOP.title": "Gelatina",
  "TWIG_SLIME_S.moves.TACKLE.title": "Azione",
  "TWIG_SLIME_S.name": "Ramomelma (piccola)",
  "TWO_TAILED_RAT.moves.CALL_FOR_BACKUP.title": "Rinforzi",
  "TWO_TAILED_RAT.moves.DISEASE_BITE.title": "Morso patologico",
  "TWO_TAILED_RAT.moves.SCRATCH.title": "Graffio",
  "TWO_TAILED_RAT.moves.SCREECH.title": "Urlo",
  "TWO_TAILED_RAT.name": "Topo bicoda",
  "VANTOM.moves.DISMEMBER.title": "Dismembrazione",
  "VANTOM.moves.INKY_LANCE.title": "Lancia a inchiostro",
  "VANTOM.moves.INK_BLOT.title": "Macchia d'inchiostro",
  "VANTOM.moves.PREPARE.title": "Preparazione",
  "VANTOM.name": "Vantom",
  "VINE_SHAMBLER.moves.CHOMP.title": "Sgranocchio",
  "VINE_SHAMBLER.moves.GRASPING_VINES.title": "Liane arrampicanti",
  "VINE_SHAMBLER.moves.SWIPE.title": "Scippo",
  "VINE_SHAMBLER.name": "Groviglio di liane",
  "WATERFALL_GIANT.moves.PRESSURE_GUN.title": "Pistola a pressione",
  "WATERFALL_GIANT.moves.PRESSURIZE.title": "Pressione",
  "WATERFALL_GIANT.moves.RAM.title": "Incornata",
  "WATERFALL_GIANT.moves.SIPHON.title": "Appropriazione",
  "WATERFALL_GIANT.moves.STOMP.title": "Pestone",
  "WATERFALL_GIANT.name": "Gigante della cascata",
  "WRIGGLER.moves.PARASITIZE_PLAYER.title": "Parassita",
  "WRIGGLER.moves.WRIGGLE_STRIKE.title": "Colpo con larve",
  "WRIGGLER.name": "Larva",
  "ZAPBOT.moves.ZAP.title": "Scarica",
  "ZAPBOT.name": "Elettrobot"
}
