{
  "ADROIT.description": "Дает [blue]{Block:diff()}[/blue] [gold]защиты[/gold].",
  "ADROIT.extraCardText": "Дает {Block:diff()} [gold]защиты[/gold].",
  "ADROIT.title": "Смекалка",
  "CLONE.description": "Эту карту можно удвоить в [gold]лагере[/gold].",
  "CLONE.title": "Удвоение",
  "CORRUPTED.description": "Наносит на [blue]50%[/blue] больше урона, но отнимает [blue]2[/blue] ОЗ.",
  "CORRUPTED.dialogue": "Непревзойденная сила…",
  "CORRUPTED.extraCardText": "Отнимает 2 ОЗ.",
  "CORRUPTED.title": "Чудовищная",
  "DEPRECATED_ENCHANTMENT.description": "Этих чар больше нет в игре.",
  "DEPRECATED_ENCHANTMENT.title": "Устаревшая",
  "FAVORED.description": "Удваивает урон от атак этой картой.",
  "FAVORED.title": "Фаворит",
  "GLAM.description": "При первом разыгрывании в каждом бою у карты есть [gold]повтор[/gold].",
  "GLAM.title": "Шик",
  "GOOPY.description": "Карта [gold]сжигается[/gold]. При разыгрывании даваемая [gold]защита[/gold] навсегда повышается на [blue]1[/blue].",
  "GOOPY.extraCardText": "Даваемая [gold]защита[/gold] навсегда повышается на [blue]1[/blue].",
  "GOOPY.title": "Вязкая",
  "IMBUED.description": "В начале каждого боя эта карта разыгрывается автоматически.",
  "IMBUED.extraCardText": "Знаковая.",
  "IMBUED.title": "Знаковая",
  "INSTINCT.description": "Стоимость этой карты уменьшается на [blue]1[/blue].",
  "INSTINCT.title": "Инстинкт",
  "MOCK_FREE_ENCHANTMENT.title": "Бесплатные чары только в мышеловке",
  "MOMENTUM.description": "При разыгрывании урон этой карты повышается на [blue]{Amount}[/blue] до конца боя.",
  "MOMENTUM.extraCardText": "Урон от карты повышается на {Amount} до конца боя.",
  "MOMENTUM.title": "Размах",
  "NIMBLE.description": "Повышает даваемую [gold]защиту[/gold] на [blue]{Amount}[/blue].",
  "NIMBLE.title": "Гибкость",
  "PERFECT_FIT.description": "При перемешивании [gold]стопки добора[/gold] эта карта кладется на верх.",
  "PERFECT_FIT.extraCardText": "Свое место.",
  "PERFECT_FIT.title": "Свое место",
  "ROYALLY_APPROVED.description": "Эта карта становится [gold]начальной[/gold] и [gold]оставляется[/gold].",
  "ROYALLY_APPROVED.title": "Королевская печать",
  "SHARP.description": "Урон от этой карты повышается на [blue]{Amount}[/blue].",
  "SHARP.title": "Острая",
  "SLITHER.description": "Когда вы берете эту карту, ее стоимость становится случайной (от [blue]0[/blue] до [blue]3[/blue]).",
  "SLITHER.title": "Зигзаг",
  "SLUMBERING_ESSENCE.description": "Если эта карта находится в руке в конце хода, ее стоимость снижается на [blue]1[/blue]пока вы ее не разыграете.",
  "SLUMBERING_ESSENCE.title": "Дремлющая эссенция",
  "SOULS_POWER.description": "Эта карта больше не [gold]сжигается[/gold].",
  "SOULS_POWER.title": "Искра души",
  "SOWN.description": "Эта карта дает {Amount:energyIcons()} при первом разыгрывании в каждом бою.",
  "SOWN.extraCardText": "Дает {Amount:energyIcons()}.",
  "SOWN.title": "Посев",
  "SPIRAL.description": "Эта карта получает [blue]1[/blue] [gold]повтор[/gold].",
  "SPIRAL.title": "Спираль",
  "STEADY.description": "Эта карта [gold]оставляется[/gold].",
  "STEADY.title": "Надежность",
  "SWIFT.description": "При первом разыгрывании в каждом бою вы берете [blue]{Amount}[/blue] {Amount:plural(ru):карту|карты|карт}.",
  "SWIFT.extraCardText": "Вы берете {Amount} {Amount:plural(ru):карту|карты|карт} при первом разыгрывании этой карты.",
  "SWIFT.title": "Скорость",
  "TEZCATARAS_EMBER.description": "Карта становится [blue]бесплатной[/blue] и [gold]вечной[/gold].",
  "TEZCATARAS_EMBER.title": "Уголек Тецкатары",
  "VIGOROUS.description": "При первом разыгрывании в каждом бою эта карта наносит на [blue]{Amount}[/blue] больше урона.",
  "VIGOROUS.title": "Бодрость"
}
