{
  "ACKNOWLEDGE_BUTTON": "Poursuivre",
  "EPOCH_INSPECT.chapterFormat": "Chapitre {ChapterIndex} - {ChapterName}",
  "EPOCH_INSPECT.closeButton": "Fermer",
  "EPOCH_INSPECT.continueButton": "Poursuivre",
  "EPOCH_INSPECT.unlockButton": "Débloquer",
  "PLACEHOLDER_PORTRAIT": "Placeholder",
  "REMINDER_TEXT": "{RevealableEpochCount} {RevealableEpochCount:plural:Ère reste|Ères restent} à découvrir...",
  "REVEAL_TIP_HEADER": "Prérequis",
  "TUTORIAL_TEXT": "Dans la [blue]Frise temporelle[/blue], vous pouvez découvrir des [gold]Ères[/gold] afin de débloquer des cartes, des reliques, et bien plus...",
  "UNLOCK_ANCIENT": "Ancien débloqué : Darv, l'Amasseur, pourra désormais apparaître dans vos parties...",
  "UNLOCK_CARDS": "Les cartes suivantes pourront apparaître dans les parties à venir.",
  "UNLOCK_CARDS_BANNER": "Cartes débloquées !",
  "UNLOCK_CONFIRM": "Confirmer",
  "UNLOCK_EPOCHS": "La Frise s'allonge...",
  "UNLOCK_POTIONS": "Les potions suivantes pourront apparaître dans les parties à venir.",
  "UNLOCK_POTIONS_BANNER": "Potions débloquées !",
  "UNLOCK_RELICS": "Les reliques suivantes pourront apparaître dans les parties à venir.",
  "UNLOCK_RELICS_BANNER": "Reliques débloquées !",
  "UNLOCK_TEXT.cards": "Cartes débloquées : {Card1}, {Card2} et {Card3}.",
  "UNLOCK_TEXT.potions": "Potions débloquées : {Potion1}, {Potion2} et {Potion3}.",
  "UNLOCK_TEXT.relics": "Reliques débloquées : {Relic1}, {Relic2} et {Relic3}."
}
